faust_pydantic_validate/__init__.py
faust_pydantic_validate/wrappers.py
faust_pydantic_validate-0.0.2.dist-info/METADATA
faust_pydantic_validate-0.0.2.dist-info/WHEEL
faust_pydantic_validate-0.0.2.dist-info/top_level.txt
faust_pydantic_validate-0.0.2.dist-info/RECORD
