Metadata-Version: 2.1
Name: faust-pydantic-validate
Version: 0.0.2
Summary: A small decorator for post data view validation
Home-page: https://github.com/Kuzyashin/faust-pydantic-validate
Author: Alexey Kuzyashin
Author-email: alex@rocketcompute.com
License: UNKNOWN
Platform: UNKNOWN
Classifier: Programming Language :: Python :: 3
Classifier: License :: OSI Approved :: MIT License
Classifier: Operating System :: OS Independent
Requires-Python: >=3.6
Requires-Dist: pydantic
Requires-Dist: faust-streaming
